README.rst
setup.py
bin/p2pshare
p2pshare/Peer.py
p2pshare/__init__.py
p2pshare.egg-info/PKG-INFO
p2pshare.egg-info/SOURCES.txt
p2pshare.egg-info/dependency_links.txt
p2pshare.egg-info/not-zip-safe
p2pshare.egg-info/top_level.txt