Metadata-Version: 1.0
Name: p2pshare
Version: 0.1
Summary: Peer to Peer file sharing Network
Home-page: http://github.com/shanmbic/p2pshare
Author: Shantanu
Author-email: shantanu1002@gmail.com
License: LICENSE.rst
Platform: UNKNOWN
